saturnin/core/__about__.py
saturnin/core/__init__.py
saturnin/core/binary_reader/__init__.py
saturnin/core/binary_reader/api.py
saturnin/core/binary_reader/service.py
saturnin/core/binary_writer/__init__.py
saturnin/core/binary_writer/api.py
saturnin/core/binary_writer/service.py
saturnin/core/fb_log_fromsrv/__init__.py
saturnin/core/fb_log_fromsrv/api.py
saturnin/core/fb_log_fromsrv/service.py
saturnin/core/fb_log_parse/__init__.py
saturnin/core/fb_log_parse/api.py
saturnin/core/fb_log_parse/service.py
saturnin/core/fb_trace_parse/__init__.py
saturnin/core/fb_trace_parse/api.py
saturnin/core/fb_trace_parse/service.py
saturnin/core/fb_trace_session/__init__.py
saturnin/core/fb_trace_session/api.py
saturnin/core/fb_trace_session/service.py
saturnin/core/proto_aggregator/__init__.py
saturnin/core/proto_aggregator/api.py
saturnin/core/proto_aggregator/service.py
saturnin/core/proto_filter/__init__.py
saturnin/core/proto_filter/api.py
saturnin/core/proto_filter/service.py
saturnin/core/proto_printer/__init__.py
saturnin/core/proto_printer/api.py
saturnin/core/proto_printer/service.py
saturnin/core/protobuf/__init__.py
saturnin/core/protobuf/common_pb2.py
saturnin/core/protobuf/common_pb2.pyi
saturnin/core/protobuf/fblog_pb2.py
saturnin/core/protobuf/fblog_pb2.pyi
saturnin/core/protobuf/fbtrace_pb2.py
saturnin/core/protobuf/fbtrace_pb2.pyi
saturnin/core/text_filter/__init__.py
saturnin/core/text_filter/api.py
saturnin/core/text_filter/service.py
saturnin/core/text_reader/__init__.py
saturnin/core/text_reader/api.py
saturnin/core/text_reader/service.py
saturnin/core/text_writer/__init__.py
saturnin/core/text_writer/api.py
saturnin/core/text_writer/service.py
saturnin_core-0.10.0.dist-info/METADATA
saturnin_core-0.10.0.dist-info/WHEEL
saturnin_core-0.10.0.dist-info/entry_points.txt
saturnin_core-0.10.0.dist-info/licenses/LICENSE
saturnin_core-0.10.0.dist-info/RECORD
