Metadata-Version: 2.4
Name: saturnin-core
Version: 0.10.0
Summary: Saturnin core services
Project-URL: Home, http://firebirdsql.org/en/saturnin/
Project-URL: Documentation, https://saturnin-core.rtfd.io
Project-URL: Issues, https://github.com/FirebirdSQL/saturnin-core/issues
Project-URL: Funding, https://github.com/sponsors/pcisar
Project-URL: Source, https://github.com/FirebirdSQL/saturnin-core
Author-email: Pavel Cisar <pcisar@users.sourceforge.net>
License: MIT License
License-File: LICENSE
Keywords: Butler,Core,Firebird,Platform,Saturnin,Services,ZeroMQ
Classifier: Development Status :: 4 - Beta
Classifier: Intended Audience :: Developers
Classifier: Intended Audience :: System Administrators
Classifier: License :: OSI Approved :: MIT License
Classifier: Operating System :: MacOS
Classifier: Operating System :: Microsoft :: Windows
Classifier: Operating System :: POSIX :: Linux
Classifier: Programming Language :: Python :: 3 :: Only
Classifier: Programming Language :: Python :: 3.11
Classifier: Programming Language :: Python :: 3.12
Classifier: Programming Language :: Python :: 3.13
Classifier: Topic :: Database
Classifier: Topic :: System :: Logging
Classifier: Topic :: System :: Monitoring
Classifier: Topic :: System :: Systems Administration
Requires-Python: >=3.11
Requires-Dist: firebird-driver~=2.0
Requires-Dist: firebird-lib~=2.0
Requires-Dist: saturnin==0.10.0
